{"creation date":"Tue, 19 May 2020 20:11:44 GMT","generals":{"mission name":"M1","starting date":"2000-01-01 12:00:00.000","end date":"2000-01-02 13:00:00.000","time step":"50","perturbations":["LS","J2","SPR"],"ephemerides file":"./ephmerides.txt"},"celestial bodies":{"to load":["Sun","Earth","Moon"]},"satellites":[{"r0":[42000000,0,0],"v0":[0,3078,0],"mass":792,"surface":20,"name":"SAT1","corps_ref":"Earth","maneuvers":[]},{"r0":[46000000,0,0],"v0":[0,2678,0],"mass":792,"surface":20,"name":"SAT2","corps_ref":"Earth","maneuvers":[]},{"name":"SAT3","mass":500,"corps_ref":"Earth","surface":50,"r0":[10000,0,0],"v0":[0,8000,0],"maneuvers":[]}],"exploitation":{"space view":{"on":true},"ground track":{"on":true,"sat_names":[]},"graphics":{"on":true,"values":{"i":["SAT3"]}}}}